LICENSE
README.md
setup.py
helpers/__init__.py
helpers/apps.py
helpers/authentication.py
helpers/custom_schemas.py
helpers/filter_models.py
helpers/global_vars.py
helpers/models.py
helpers/models_schema_fields.py
helpers/monitoring.py
helpers/permissions.py
helpers/requests.py
helpers/serializers.py
helpers/users.py
helpers/validators.py
helpers/views.py
helpers/middleware/__init__.py
helpers/middleware/language.py
helpers/middleware/locale.py
helpers/middleware/profession_id.py
helpers/middleware/software.py
helpers/middleware/specialty_id.py
helpers/middleware/user_agent.py
helpers/middleware/user_uid.py
tonicapp_helpers.egg-info/PKG-INFO
tonicapp_helpers.egg-info/SOURCES.txt
tonicapp_helpers.egg-info/dependency_links.txt
tonicapp_helpers.egg-info/requires.txt
tonicapp_helpers.egg-info/top_level.txt