Metadata-Version: 2.1
Name: tonicapp-helpers
Version: 3.7.0
Summary: Toolbox with general functions and models to avoid repetition.
Home-page: UNKNOWN
Author: tonicapp
Author-email: web@tonicapp.com
License: MIT License
Platform: UNKNOWN
Classifier: Environment :: Web Environment
Classifier: Framework :: Django
Classifier: Intended Audience :: Developers
Classifier: License :: OSI Approved :: MIT License
Classifier: Operating System :: OS Independent
Classifier: Programming Language :: Python
Classifier: Programming Language :: Python :: 3.6
Classifier: Topic :: Internet :: WWW/HTTP
License-File: LICENSE
